{
  "address": "385 Corbett Avenue, San Francisco, CA 94114",
  "path": "/san-francisco/corbett-heights/corbett-avenue/385/",
  "apn": "2704021",
  "block": "2704",
  "lot": "021",
  "coordinates": { "lat": 37.759249, "lng": -122.445652 },
  "parcel": {
    "year_built": 1955,
    "use": "Single Family Residential",
    "property_class": "Dwelling",
    "units": 1,
    "stories": 2,
    "rooms": 6,
    "construction_type_code": "D",
    "lot_area_sqft": 2922,
    "building_area_sqft": 1474,
    "zoning": "RH-2",
    "supervisor_district": 8
  },
  "historic_status": {
    "ceqa_status_code": "B",
    "ceqa_status_label": "Unknown Historic Resource status",
    "reason": "No evaluation and 45 years or older",
    "designated_landmark": false,
    "source": "sf-planning"
  },
  "building_history": {
    "contractor": "Elis J. Ekstrom",
    "contractor_note": "Also built 100–102 Corbett Avenue.",
    "architect": null,
    "architect_note": "An architect was engaged; not named in the record.",
    "built_on": "a previously vacant lot",
    "source": "corbett-heights-neighbors"
  },
  "sources": [
    { "id": "corbett-heights-neighbors",
      "name": "Corbett Heights Neighbors, \"July Neighborhood News\", Vol. VIII, No. 7 (1 July 2026)",
      "query": "https://corbettneighbors.optin.com/newsletter/awlist6655060/MzAxMzAwMzY=/july-neighborhood-news.htm",
      "retrieved": "2026-07-22" },
    { "id": "sf-eas-addresses", "name": "SF Enterprise Addressing System via DataSF",
      "query": "https://data.sfgov.org/resource/3mea-di5p.json?street_name=CORBETT&street_type=AVE&address_number=385",
      "retrieved": "2026-07-22" },
    { "id": "sf-assessor-roll", "name": "SF Office of the Assessor-Recorder via DataSF (2025 secured roll)",
      "query": "https://data.sfgov.org/resource/wv5m-vpq2.json?parcel_number=2704021&$order=closed_roll_year%20DESC&$limit=1",
      "retrieved": "2026-07-22" },
    { "id": "sf-planning", "name": "SF Planning Department — Historic Resource Status by Parcel via DataSF",
      "query": "https://data.sfgov.org/resource/3tsw-4idn.json?apn=2704021",
      "retrieved": "2026-07-22" }
  ]
}
