{
  "address": "711–715 Castro Street, San Francisco, CA 94114",
  "address_range": { "low": 711, "high": 715, "canonical": 711,
    "note": "One parcel and one building spanning three street numbers (711, 713, 715). Permits are filed under all three numbers; the DBI records are the same." },
  "path": "/san-francisco/castro/castro-street/711/",
  "apn": "3603073",
  "block": "3603",
  "lot": "073",
  "coordinates": { "lat": 37.757444, "lng": -122.434344 },
  "parcel": {
    "year_built": 1900,
    "use": "Multi-Family Residential",
    "property_class": "Flats & Duplex",
    "units": 3,
    "stories": 3,
    "rooms": 16,
    "lot_area_sqft": 2622,
    "building_area_sqft": 5280,
    "zoning": "RH-3",
    "supervisor_district": 8,
    "analysis_neighborhood": "Castro/Upper Market"
  },
  "historic_status": {
    "ceqa_status_code": "A",
    "ceqa_status_label": "Historical Resource present",
    "reason": "California Register Historic District, Historic Survey Result",
    "district": {
      "name": "Castro & Liberty Streets Historic District",
      "california_register": "Eligible",
      "national_register": "No",
      "article_10_local_landmark_district": false,
      "period_of_significance": "1897-1906",
      "source": "sf-planning"
    },
    "designated_landmark": false,
    "source": "sf-planning"
  },
  "assessment": {
    "roll_year": 2025,
    "assessed_land_value": 258854,
    "assessed_improvement_value": 537658,
    "note": "No sale date recorded on the 2025 roll."
  },
  "permits": [
    { "number": "201004200672", "status": "complete", "filed": "2010-04-20", "estimated_cost": 7500,
      "description": "revision adding dry rot repair at rear walls and stairs", "source": "sf-building-permits" },
    { "number": "200912082817", "status": "complete", "filed": "2009-12-08", "estimated_cost": 40000,
      "description": "dry rot repair and voluntary strengthening, like for like", "source": "sf-building-permits" },
    { "number": "200910300184", "status": "complete", "filed": "2009-10-30", "estimated_cost": 15000,
      "description": "dry rot repair at rear wall, replaced in kind, about 400 ft at the right rear corner", "source": "sf-building-permits" },
    { "number": "8600646", "status": "complete", "filed": "1986-01-16", "estimated_cost": 0,
      "cost_note": "No cost recorded in the dataset.",
      "description": "foundation, rear stairs and pier post repaired; wood floor removed", "source": "sf-building-permits" },
    { "number": "8511328", "status": "cancelled", "filed": "1985-10-08", "estimated_cost": 5000,
      "description": "convert a portion of the basement to a garage", "source": "sf-building-permits" },
    { "number": "8508457", "status": "complete", "filed": "1985-08-06", "estimated_cost": 5000,
      "description": "rear metal fire escape added from the third floor", "source": "sf-building-permits" },
    { "number": "8508008", "status": "complete", "filed": "1985-07-29", "estimated_cost": 3000,
      "description": "completion of work begun under application 8310056", "source": "sf-building-permits" },
    { "number": "8406831", "status": "cancelled", "filed": "1984-06-22", "estimated_cost": 3000,
      "description": "replace windows and roof", "source": "sf-building-permits" },
    { "number": "8402060", "status": "cancelled", "filed": "1984-02-28", "estimated_cost": 600,
      "description": "replace existing window frames", "source": "sf-building-permits" },
    { "number": "8310056", "status": "expired", "filed": "1983-10-06", "estimated_cost": 2500,
      "description": "replace dry-rotted roof and wood windows", "source": "sf-building-permits" },
    { "number": "8309354", "status": "cancelled", "filed": "1983-09-20", "estimated_cost": 26,
      "description": "remove rolled roof", "source": "sf-building-permits" }
  ],
  "permits_note": "13 permits on file across street numbers 711, 713 and 715 — the same parcel. Two $1 administrative filings (a street-space permit and a plan-dimension correction) are omitted from the page.",
  "sources": [
    { "id": "sf-eas-addresses", "name": "SF Enterprise Addressing System via DataSF",
      "query": "https://data.sfgov.org/resource/3mea-di5p.json?street_name=CASTRO&street_type=ST&address_number=711",
      "retrieved": "2026-07-21" },
    { "id": "sf-assessor-roll", "name": "SF Office of the Assessor-Recorder via DataSF (2025 secured roll)",
      "query": "https://data.sfgov.org/resource/wv5m-vpq2.json?parcel_number=3603073&$order=closed_roll_year%20DESC&$limit=1",
      "retrieved": "2026-07-21" },
    { "id": "sf-building-permits", "name": "SF Dept. of Building Inspection via DataSF",
      "query": "https://data.sfgov.org/resource/i98e-djp9.json?street_number=715&street_name=Castro",
      "retrieved": "2026-07-21" },
    { "id": "sf-planning", "name": "SF Planning Department — Historic Resource Status by Parcel, and Historic Districts, via DataSF",
      "query": "https://data.sfgov.org/resource/3tsw-4idn.json?apn=3603073",
      "retrieved": "2026-07-21" }
  ]
}
